repeatfinder.cpython-38-darwin.so
repeatfinder-1.10.data/scripts/repeatfinder.py
repeatfinder-1.10.dist-info/LICENSE.txt
repeatfinder-1.10.dist-info/METADATA
repeatfinder-1.10.dist-info/WHEEL
repeatfinder-1.10.dist-info/top_level.txt
repeatfinder-1.10.dist-info/RECORD
