Metadata-Version: 2.1
Name: repeatfinder
Version: 1.10
Summary: A package for finding repeats in a DNA sequence
Home-page: https://github.com/deprekate/RepeatFinder
Author: Katelyn McNair
Author-email: deprekate@gmail.com
License: UNKNOWN
Platform: UNKNOWN
Classifier: Programming Language :: Python :: 3
Classifier: License :: OSI Approved :: MIT License
Classifier: Operating System :: OS Independent
Requires-Python: >3.5.2
License-File: LICENSE.txt
Requires-Dist: genbank
